scml_agents/__init__.py
scml_agents/__main__.py
scml_agents/agents.py
scml_agents/contrib/__init__.py
scml_agents/scml2019/__init__.py
scml_agents/scml2019/fj2.py
scml_agents/scml2019/iffm.py
scml_agents/scml2019/monopoly.py
scml_agents/scml2019/psfm.py
scml_agents/scml2019/rapt_fm.py
scml_agents/scml2019/saha.py
scml_agents/scml2019/cheap_buyer/ConsumerUtilityFunction.py
scml_agents/scml2019/cheap_buyer/MyNegotiator2.py
scml_agents/scml2019/cheap_buyer/NegotiationStepsDataHolder.py
scml_agents/scml2019/cheap_buyer/SellerUtilityFunction.py
scml_agents/scml2019/cheap_buyer/__init__.py
scml_agents/scml2019/cheap_buyer/cheapbuyer.py
scml_agents/scml2019/cheap_buyer/my_negotiator.py
scml_agents/scml2019/cheap_buyer/my_test_negotiator.py
scml_agents/scml2019/cheap_buyer/myconsumer.py
scml_agents/scml2019/cheap_buyer/myscheduler.py
scml_agents/scml2019/cheap_buyer/myutilityfunction.py
scml_agents/scml2019/nvm/__init__.py
scml_agents/scml2019/nvm/agent_brain.py
scml_agents/scml2019/nvm/data_generate.py
scml_agents/scml2019/nvm/gen_qtty_feasible_domain_cp.py
scml_agents/scml2019/nvm/mp_nvp.py
scml_agents/scml2019/nvm/mp_nvp_lp.py
scml_agents/scml2019/nvm/newsvendor.py
scml_agents/scml2019/nvm/nmv_agent.py
scml_agents/scml2019/nvm/pydata.py
scml_agents/scml2020/__init__.py
scml_agents/scml2020/a_sengupta/__init__.py
scml_agents/scml2020/a_sengupta/agent1_mod.py
scml_agents/scml2020/agent0x111/__init__.py
scml_agents/scml2020/agent0x111/agent.py
scml_agents/scml2020/bargent/__init__.py
scml_agents/scml2020/bargent/anewagent.py
scml_agents/scml2020/bargent/negotiation_strategy.py
scml_agents/scml2020/bargent/production_strategy.py
scml_agents/scml2020/bargent/trading_strategy.py
scml_agents/scml2020/biu_th/__init__.py
scml_agents/scml2020/biu_th/agent.py
scml_agents/scml2020/biu_th/controller.py
scml_agents/scml2020/biu_th/negotiation_manager.py
scml_agents/scml2020/monty_hall/__init__.py
scml_agents/scml2020/monty_hall/contractstest.py
scml_agents-0.1.1.dist-info/AUTHORS.rst
scml_agents-0.1.1.dist-info/LICENSE
scml_agents-0.1.1.dist-info/METADATA
scml_agents-0.1.1.dist-info/WHEEL
scml_agents-0.1.1.dist-info/top_level.txt
scml_agents-0.1.1.dist-info/RECORD
