Metadata-Version: 2.1
Name: scml-agents
Version: 0.1.1
Summary: Agents submitted to the SCML competition or contributed by the community
Home-page: https://github.com/yasserfarouk/scml-agents
Author: Yasser Mohammad
Author-email: yasserfarouk@gmail.com
License: UNKNOWN
Project-URL: homepage, https://github.com/yasserfarouk/negmas
Keywords: negotiation mas multi-agent simulation AI
Platform: UNKNOWN
Classifier: License :: OSI Approved :: GNU General Public License v2 or later (GPLv2+)
Classifier: Programming Language :: Python :: 3
Classifier: Programming Language :: Python :: 3.6
Classifier: Programming Language :: Python :: 3.7
Classifier: Programming Language :: Python :: 3.8
Requires-Python: >=3.6
Requires-Dist: Click (>=6.0)
Requires-Dist: torch
Requires-Dist: tensorflow-cpu
Requires-Dist: scml
Requires-Dist: dataclasses ; python_version < "3.7"
